{
  "_id": "{D1CB87C7-D89F-4583-9DA8-5372DC59F25A}",
  "clientAppType": "testXpert III",
  "state": "finishedOK",
  "tags": [
    "{B9D90822-09A8-4eab-871B-70FD0C1B4CD3}"
  ],
  "version": "2.1772195387.0",
  "valueColumns": [
    {
      "unitTableId": "Zwick.Unittable.Displacement",
      "valueTableId": "{E4C21909-B178-4fdc-8662-A13B4C7FF756}-Zwick.Unittable.Displacement",
      "_id": "{E4C21909-B178-4fdc-8662-A13B4C7FF756}-Zwick.Unittable.Displacement_Key",
      "name": "Strain / Deformation",
    },
   ...
  ],
  "hasMachineConfigurationInfo": false,
  "testProgramId": "TestProgram_2",
  "testProgramVersion": "2.1772195387.0",
  "name": "01",
  "modifiedOn": {},
  "TestParametersFlat": {
    "TYPE_OF_TESTING_STR": "tensile",
    "MACHINE_TYPE_STR": "Static",
    "STANDARD": "DIN EN ",
    "TESTER": "Tester_1",
    "NOTES": "Auswertung E-Modul nach ClipOn Punkten",
    "Wall thickness": 0.002,
    "SPECIMEN_THICKNESS": 0.001925,
    "SPECIMEN_WIDTH": 0.015075,
    "Diameter": 0.00011,
    "Outer diameter": 0.1,
    "Inner diameter": 0.008,
    "Fineness": 0.00001,
    "Density of the specimen material": 1000,
    "Weight of the specimen": 0.001,
    "Total length of the specimen": 0.1,
    "Cross-section input": 0.000001,
    "Parallel specimen length": 0.1,
    "Marked initial gage length": 0.08,
    "TEST_SPEED": 0.0000333333333333,
    "Date": "26.11.2021",
    "Upper force limit": 3000,
    "Maximum extension": 0.005,
    "Cross-section correction factor": 1,
    "Negative cross-section correction value": 0,
    "Grip to grip separation at the start position": 0.1227327709145275,
    "Type of Young's modulus determination": 1,
    "Begin of Young's modulus determination": 0.0005,
    "End of Young's modulus determination": 0.0025,
    "Force shutdown threshold": 20,
    "Gage length, fine strain": 0.02,
    "Speed, Young's modulus": 0.0000166666666667,
    "Speed, point of load removal": 0.0008333333333333,
    "Speed, yield point": 0.0000166666666667,
    "Max. permissible force at end of test": 250,
    "Tube definition": 2,
    "Travel preset x1%": 0.01,
    "Travel preset x2%": 0.02,
    "Young's modulus preset": 210000000000,
    "JOB_NO": "11918",
    "CUSTOMER": "Company_1",
    "SPECIMEN_TYPE": "IPS",
    "Headline for the report": "Prüfprotokoll",
    "Clock time": "09:42:38",
    "Gage length after break": 0.12,
    "Diameter 1 after break": 0.002,
    "Diameter 2 after break": 0.009,
    "Specimen thickness after break": 0.002,
    "Specimen width after break": 0.005,
    "Cross-section after break": 0
  }
}